shiphelm/__init__.py
shiphelm/helm.py
shiphelm/helmdocker.py
shiphelm/helmkube.py
shiphelm/helmswarm.py
Shiphelm-0.8.0.dist-info/LICENSE
Shiphelm-0.8.0.dist-info/METADATA
Shiphelm-0.8.0.dist-info/WHEEL
Shiphelm-0.8.0.dist-info/top_level.txt
Shiphelm-0.8.0.dist-info/RECORD
