Metadata-Version: 2.1
Name: Shiphelm
Version: 0.8.0
Summary: Docker and kubernetes integration library
Home-page: https://gameplex-software.github.io/ShipHelm/
Author: Gameplex Software
Author-email: info@gameplexsoftware.com
Keywords: SkiffUI,kubernetes,docker
Classifier: Development Status :: 5 - Production/Stable
Classifier: Intended Audience :: Developers
Classifier: Topic :: Software Development :: Build Tools
Classifier: Programming Language :: Python :: 3.7
Classifier: Programming Language :: Python :: 3.8
Classifier: Programming Language :: Python :: 3.9
Classifier: Programming Language :: Python :: 3 :: Only
Classifier: License :: OSI Approved :: MIT License
Classifier: Operating System :: OS Independent
Requires-Python: >=3.7
License-File: LICENSE
Requires-Dist: docker
Provides-Extra: dev
Requires-Dist: check-manifest ; extra == 'dev'
